folium/__init__.py
folium/_version.py
folium/elements.py
folium/features.py
folium/folium.py
folium/map.py
folium/raster_layers.py
folium/template.py
folium/utilities.py
folium/vector_layers.py
folium/plugins/__init__.py
folium/plugins/antpath.py
folium/plugins/beautify_icon.py
folium/plugins/boat_marker.py
folium/plugins/draw.py
folium/plugins/dual_map.py
folium/plugins/encoded.py
folium/plugins/fast_marker_cluster.py
folium/plugins/feature_group_sub_group.py
folium/plugins/float_image.py
folium/plugins/fullscreen.py
folium/plugins/geocoder.py
folium/plugins/groupedlayercontrol.py
folium/plugins/heat_map.py
folium/plugins/heat_map_withtime.py
folium/plugins/locate_control.py
folium/plugins/marker_cluster.py
folium/plugins/measure_control.py
folium/plugins/minimap.py
folium/plugins/mouse_position.py
folium/plugins/pattern.py
folium/plugins/polyline_offset.py
folium/plugins/polyline_text_path.py
folium/plugins/realtime.py
folium/plugins/scroll_zoom_toggler.py
folium/plugins/search.py
folium/plugins/semicircle.py
folium/plugins/side_by_side.py
folium/plugins/tag_filter_button.py
folium/plugins/terminator.py
folium/plugins/time_slider_choropleth.py
folium/plugins/timeline.py
folium/plugins/timestamped_geo_json.py
folium/plugins/timestamped_wmstilelayer.py
folium/plugins/treelayercontrol.py
folium/plugins/vectorgrid_protobuf.py
folium/templates/leaflet_heat.min.js
folium/templates/pa7_hm.min.js
folium/templates/pa7_leaflet_hm.min.js
folium-0.17.0.dist-info/LICENSE.txt
folium-0.17.0.dist-info/METADATA
folium-0.17.0.dist-info/WHEEL
folium-0.17.0.dist-info/top_level.txt
folium-0.17.0.dist-info/RECORD
