Metadata-Version: 2.1
Name: folium
Version: 0.17.0
Summary: Make beautiful maps with Leaflet.js & Python
Home-page: https://github.com/python-visualization/folium
Author: Rob Story
Author-email: wrobstory@gmail.com
License: MIT
Keywords: data visualization
Platform: any
Classifier: Programming Language :: Python :: 3.8
Classifier: Programming Language :: Python :: 3.9
Classifier: Programming Language :: Python :: 3.10
Classifier: Programming Language :: Python :: 3.11
Classifier: Programming Language :: Python :: 3.12
Classifier: Topic :: Scientific/Engineering :: GIS
Classifier: Topic :: Scientific/Engineering :: Visualization
Classifier: License :: OSI Approved :: MIT License
Classifier: Development Status :: 5 - Production/Stable
Requires-Python: >=3.8
License-File: LICENSE.txt
Requires-Dist: branca>=0.6.0
Requires-Dist: jinja2>=2.9
Requires-Dist: numpy
Requires-Dist: requests
Requires-Dist: xyzservices
Provides-Extra: testing
Requires-Dist: pytest; extra == "testing"
